just_start/__init__.py
just_start/_just_start.py
just_start/client_example.py
just_start/config_reader.py
just_start/constants.py
just_start/logging.py
just_start/os_utils.py
just_start/pomodoro.py
just_start/py.typed
just_start_urwid/__init__.py
just_start_urwid/__main__.py
just_start_urwid/client.py
just_start_urwid/py.typed
just_start-0.5.2.dist-info/entry_points.txt
just_start-0.5.2.dist-info/LICENSE
just_start-0.5.2.dist-info/WHEEL
just_start-0.5.2.dist-info/METADATA
just_start-0.5.2.dist-info/RECORD
