Metadata-Version: 2.1
Name: just-start
Version: 0.5.2
Summary: Just Start is a wrapper for Task Warrior with pomodoro support
Home-page: https://github.com/AliGhahraei/just-start/
License: GPL-3.0+
Author: Ali Ghahraei
Author-email: aligf94@gmail.com
Requires-Python: >=3.10,<4.0
Classifier: License :: OSI Approved :: GNU General Public License v3 or later (GPLv3+)
Classifier: Programming Language :: Python :: 3
Classifier: Programming Language :: Python :: 3.10
Provides-Extra: term
Provides-Extra: urwid
Requires-Dist: pexpect (>=4.6,<5.0)
Requires-Dist: pydantic (>=1.8.2,<2.0.0)
Requires-Dist: toml (>=0.10.0,<0.11.0)
Requires-Dist: urwid (>=2.0,<3.0); extra == "urwid"
Project-URL: Repository, https://github.com/AliGhahraei/just-start/
